bytepatches/__init__.py
bytepatches/decorators.py
bytepatches/op_replacer.py
bytepatches/ops.py
bytepatches/parser.py
bytepatches/utils.py
bytepatches-0.0.1.dist-info/METADATA
bytepatches-0.0.1.dist-info/WHEEL
bytepatches-0.0.1.dist-info/top_level.txt
bytepatches-0.0.1.dist-info/RECORD
