Metadata-Version: 2.1
Name: bytepatches
Version: 0.0.1
Summary: A high-level bytecode parser and modifier
Home-page: https://github.com/martmists/bytepatches
Author: martmists
Author-email: mail@martmists.com
License: MIT
Keywords: Bytecode,Python,Patch
Platform: UNKNOWN
Classifier: Development Status :: 2 - Pre-Alpha
Classifier: Operating System :: OS Independent
Classifier: Programming Language :: Python :: 3.6
Classifier: Programming Language :: Python :: 3.7
Classifier: Topic :: Software Development :: Libraries :: Python Modules
Requires-Python: >=3.6
